{"Analytics_Testbed":{"access_logs":{"analyticstestbed-access-logs-flipside-crypto":{"bucket_arn":"arn:aws:s3:::analyticstestbed-access-logs-flipside-crypto","bucket_domain_name":"analyticstestbed-access-logs-flipside-crypto.s3.amazonaws.com","bucket_id":"analyticstestbed-access-logs-flipside-crypto","bucket_prefix":"","enabled":true}},"efs_filesystems":{},"s3_buckets":{}},"Clusters_Prod":{"access_logs":{"clustersprod-access-logs-flipside-crypto":{"bucket_arn":"arn:aws:s3:::clustersprod-access-logs-flipside-crypto","bucket_domain_name":"clustersprod-access-logs-flipside-crypto.s3.amazonaws.com","bucket_id":"clustersprod-access-logs-flipside-crypto","bucket_prefix":"","enabled":true}},"efs_filesystems":{"prod-us-east-1-treasury-private":{"access_point_arns":{},"access_point_ids":{},"access_points":{},"account_id":"258529451760","account_json_key":"Clusters_Prod","accounts":["Clusters_Prod","Clusters_Stg"],"additional_security_group_rules":[],"additional_tag_map":{},"allowed_cidr_blocks":[],"allowed_security_group_ids":[],"arn":"arn:aws:elasticfilesystem:us-east-1:258529451760:file-system/fs-09644bb281c991080","associated_security_group_ids":[],"attributes":"private","availability_zone_name":null,"category":"efs_filesystems","context":{"additional_tag_map":{},"attributes":["private"],"delimiter":null,"descriptor_formats":{},"enabled":true,"environment":"prod","id_length_limit":null,"label_key_case":null,"label_order":[],"label_value_case":null,"labels_as_tags":["default"],"name":"treasury","namespace":null,"regex_replace_chars":null,"stage":"us-east-1","tags":{"Environment":"prod","Organization":"FlipsideCrypto","Owner":"DevOps","Stage":"us-east-1","Terraform":"terraform"},"tenant":null},"create_security_group":true,"delimiter":null,"descriptor_formats":{},"descriptors":{},"dns_name":"","efs_backup_policy_enabled":true,"efs_cross_account_policy_enabled":false,"enabled":true,"encrypted":true,"environment":"prod","execution_role_arn":"arn:aws:iam::258529451760:role/AWSControlTowerExecution","host":"treasury-efs-filesystems-private.clusters-prod.flipside.systems","id":"fs-09644bb281c991080","id_full":"prod-us-east-1-treasury-private","id_length_limit":null,"kms_key_id":null,"label_order":[],"mount_target_dns_names":["us-east-1a.fs-09644bb281c991080.efs.us-east-1.amazonaws.com","us-east-1b.fs-09644bb281c991080.efs.us-east-1.amazonaws.com","us-east-1c.fs-09644bb281c991080.efs.us-east-1.amazonaws.com"],"mount_target_ids":["fsmt-0c4c5d70206eea9ec","fsmt-07e5713a3184cdf50","fsmt-076b28c9030d60eca"],"mount_target_ip_address":null,"mount_target_ips":["172.20.14.149","172.20.26.57","172.20.34.178"],"name":"prod-us-east-1-treasury-private","namespace":null,"network_interface_ids":["eni-01252a201c5611b17","eni-0b17cee3377d19f9a","eni-0dac916218717b4bd"],"network_map":{"Clusters_Prod":"cluster_Clusters_Prod","Clusters_Stg":"cluster_Clusters_Stg"},"normalized_context":{"additional_tag_map":{},"attributes":["private"],"delimiter":"-","descriptor_formats":{},"enabled":true,"environment":"prod","id_length_limit":0,"label_key_case":"title","label_order":["namespace","environment","stage","name","attributes"],"label_value_case":"lower","labels_as_tags":["attributes","environment","name","namespace","stage","tenant"],"name":"treasury","namespace":"","regex_replace_chars":"/[^-a-zA-Z0-9]/","stage":"us-east-1","tags":{"Attributes":"private","Environment":"prod","Name":"prod-us-east-1-treasury-private","Organization":"FlipsideCrypto","Owner":"DevOps","Stage":"us-east-1","Terraform":"terraform"},"tenant":""},"organization":"FlipsideCrypto","owner":"DevOps","performance_mode":"generalPurpose","private":true,"provisioned_throughput_in_mibps":0,"public":false,"regex_replace_chars":null,"region":null,"security_group_arn":"arn:aws:ec2:us-east-1:258529451760:security-group/sg-02e7b6032928c64b8","security_group_create_before_destroy":true,"security_group_create_timeout":"10m","security_group_delete_timeout":"15m","security_group_description":"EFS Security Group","security_group_id":"sg-02e7b6032928c64b8","security_group_name":[],"short_name":"treasury","ssm_parameters":["/infrastructure/Clusters_Prod/efs_filesystems/prod-us-east-1-treasury-private/host"],"ssm_path_prefix":"/infrastructure/Clusters_Prod/efs_filesystems","stage":"us-east-1","subnets":[],"tags":{},"tags_as_list_of_maps":[{"key":"Attributes","value":"private"},{"key":"Environment","value":"prod"},{"key":"Name","value":"prod-us-east-1-treasury-private"},{"key":"Organization","value":"FlipsideCrypto"},{"key":"Owner","value":"DevOps"},{"key":"Stage","value":"us-east-1"},{"key":"Terraform","value":"terraform"}],"tenant":null,"terraform":"terraform","throughput_mode":"bursting","traffic":"private","transition_to_ia":["AFTER_90_DAYS"],"transition_to_primary_storage_class":[],"vpc_id":null,"zone_id":["Z0204537HSM29A830PLM"]}},"s3_buckets":{}},"Clusters_Stg":{"access_logs":{"clustersstg-access-logs-flipside-crypto":{"bucket_arn":"arn:aws:s3:::clustersstg-access-logs-flipside-crypto","bucket_domain_name":"clustersstg-access-logs-flipside-crypto.s3.amazonaws.com","bucket_id":"clustersstg-access-logs-flipside-crypto","bucket_prefix":"","enabled":true}},"efs_filesystems":{"stg-us-east-1-treasury-private":{"access_point_arns":{},"access_point_ids":{},"access_points":{},"account_id":"102758306705","account_json_key":"Clusters_Stg","accounts":["Clusters_Prod","Clusters_Stg"],"additional_security_group_rules":[],"additional_tag_map":{},"allowed_cidr_blocks":[],"allowed_security_group_ids":[],"arn":"arn:aws:elasticfilesystem:us-east-1:102758306705:file-system/fs-0c5f3a9ea106a031b","associated_security_group_ids":[],"attributes":"private","availability_zone_name":null,"category":"efs_filesystems","context":{"additional_tag_map":{},"attributes":["private"],"delimiter":null,"descriptor_formats":{},"enabled":true,"environment":"stg","id_length_limit":null,"label_key_case":null,"label_order":[],"label_value_case":null,"labels_as_tags":["default"],"name":"treasury","namespace":null,"regex_replace_chars":null,"stage":"us-east-1","tags":{"Environment":"stg","Organization":"FlipsideCrypto","Owner":"DevOps","Stage":"us-east-1","Terraform":"terraform"},"tenant":null},"create_security_group":true,"delimiter":null,"descriptor_formats":{},"descriptors":{},"dns_name":"","efs_backup_policy_enabled":true,"efs_cross_account_policy_enabled":false,"enabled":true,"encrypted":true,"environment":"stg","execution_role_arn":"arn:aws:iam::102758306705:role/AWSControlTowerExecution","host":"treasury-efs-filesystems-private.clusters-stg.flipside.kitchen","id":"fs-0c5f3a9ea106a031b","id_full":"stg-us-east-1-treasury-private","id_length_limit":null,"kms_key_id":null,"label_order":[],"mount_target_dns_names":["us-east-1a.fs-0c5f3a9ea106a031b.efs.us-east-1.amazonaws.com","us-east-1b.fs-0c5f3a9ea106a031b.efs.us-east-1.amazonaws.com","us-east-1c.fs-0c5f3a9ea106a031b.efs.us-east-1.amazonaws.com"],"mount_target_ids":["fsmt-08a83ff358ba44454","fsmt-0a9758463aab4363c","fsmt-074d3ec2e33700ee4"],"mount_target_ip_address":null,"mount_target_ips":["172.16.8.86","172.16.17.198","172.16.32.68"],"name":"stg-us-east-1-treasury-private","namespace":null,"network_interface_ids":["eni-0a82ab4d6f46ee4a8","eni-0b52b0fa87151b84d","eni-0e7c941c17192a530"],"network_map":{"Clusters_Prod":"cluster_Clusters_Prod","Clusters_Stg":"cluster_Clusters_Stg"},"normalized_context":{"additional_tag_map":{},"attributes":["private"],"delimiter":"-","descriptor_formats":{},"enabled":true,"environment":"stg","id_length_limit":0,"label_key_case":"title","label_order":["namespace","environment","stage","name","attributes"],"label_value_case":"lower","labels_as_tags":["attributes","environment","name","namespace","stage","tenant"],"name":"treasury","namespace":"","regex_replace_chars":"/[^-a-zA-Z0-9]/","stage":"us-east-1","tags":{"Attributes":"private","Environment":"stg","Name":"stg-us-east-1-treasury-private","Organization":"FlipsideCrypto","Owner":"DevOps","Stage":"us-east-1","Terraform":"terraform"},"tenant":""},"organization":"FlipsideCrypto","owner":"DevOps","performance_mode":"generalPurpose","private":true,"provisioned_throughput_in_mibps":0,"public":false,"regex_replace_chars":null,"region":null,"security_group_arn":"arn:aws:ec2:us-east-1:102758306705:security-group/sg-070425ce564e9db79","security_group_create_before_destroy":true,"security_group_create_timeout":"10m","security_group_delete_timeout":"15m","security_group_description":"EFS Security Group","security_group_id":"sg-070425ce564e9db79","security_group_name":[],"short_name":"treasury","ssm_parameters":["/infrastructure/Clusters_Stg/efs_filesystems/stg-us-east-1-treasury-private/host"],"ssm_path_prefix":"/infrastructure/Clusters_Stg/efs_filesystems","stage":"us-east-1","subnets":[],"tags":{},"tags_as_list_of_maps":[{"key":"Attributes","value":"private"},{"key":"Environment","value":"stg"},{"key":"Name","value":"stg-us-east-1-treasury-private"},{"key":"Organization","value":"FlipsideCrypto"},{"key":"Owner","value":"DevOps"},{"key":"Stage","value":"us-east-1"},{"key":"Terraform","value":"terraform"}],"tenant":null,"terraform":"terraform","throughput_mode":"bursting","traffic":"private","transition_to_ia":["AFTER_7_DAYS"],"transition_to_primary_storage_class":[],"vpc_id":null,"zone_id":["Z02041582MV8PHEUFU4M1"]}},"s3_buckets":{}},"Compass":{"access_logs":{"compass-access-logs-flipside-crypto":{"bucket_arn":"arn:aws:s3:::compass-access-logs-flipside-crypto","bucket_domain_name":"compass-access-logs-flipside-crypto.s3.amazonaws.com","bucket_id":"compass-access-logs-flipside-crypto","bucket_prefix":"","enabled":true}},"efs_filesystems":{"compass-us-east-1-compass-prod-private":{"access_point_arns":{},"access_point_ids":{},"access_points":{},"account_id":"957136710666","account_json_key":"Compass","accounts":["Compass"],"additional_security_group_rules":[],"additional_tag_map":{},"allowed_cidr_blocks":[],"allowed_security_group_ids":[],"arn":"arn:aws:elasticfilesystem:us-east-1:957136710666:file-system/fs-0ebb0208104654dcb","associated_security_group_ids":[],"attributes":"private","availability_zone_name":null,"category":"efs_filesystems","context":{"additional_tag_map":{},"attributes":["private"],"delimiter":null,"descriptor_formats":{},"enabled":true,"environment":"compass","id_length_limit":null,"label_key_case":null,"label_order":[],"label_value_case":null,"labels_as_tags":["default"],"name":"compass-prod","namespace":null,"regex_replace_chars":null,"stage":"us-east-1","tags":{"Environment":"compass","Organization":"FlipsideCrypto","Owner":"DevOps","Stage":"us-east-1","Terraform":"terraform"},"tenant":null},"create_security_group":true,"delimiter":null,"descriptor_formats":{},"descriptors":{},"dns_name":"","efs_backup_policy_enabled":true,"efs_cross_account_policy_enabled":false,"enabled":true,"encrypted":true,"environment":"compass","execution_role_arn":"arn:aws:iam::957136710666:role/AWSControlTowerExecution","host":"compass-prod-efs-filesystems-private.flompass.pizza","id":"fs-0ebb0208104654dcb","id_full":"compass-us-east-1-compass-prod-private","id_length_limit":null,"kms_key_id":null,"label_order":[],"mount_target_dns_names":["us-east-1a.fs-0ebb0208104654dcb.efs.us-east-1.amazonaws.com","us-east-1b.fs-0ebb0208104654dcb.efs.us-east-1.amazonaws.com","us-east-1c.fs-0ebb0208104654dcb.efs.us-east-1.amazonaws.com"],"mount_target_ids":["fsmt-0d6ebdb8a515122af","fsmt-0b2b948c4aef2d152","fsmt-0fe5f3bac0cd98b44"],"mount_target_ip_address":null,"mount_target_ips":["172.25.9.67","172.25.16.95","172.25.42.180"],"name":"compass-us-east-1-compass-prod-private","namespace":null,"network_interface_ids":["eni-04fead9e9b589b1e4","eni-058d4d63869f83af9","eni-02d57f1c3de09c259"],"network_map":{"Compass":"cluster_Compass"},"normalized_context":{"additional_tag_map":{},"attributes":["private"],"delimiter":"-","descriptor_formats":{},"enabled":true,"environment":"compass","id_length_limit":0,"label_key_case":"title","label_order":["namespace","environment","stage","name","attributes"],"label_value_case":"lower","labels_as_tags":["attributes","environment","name","namespace","stage","tenant"],"name":"compass-prod","namespace":"","regex_replace_chars":"/[^-a-zA-Z0-9]/","stage":"us-east-1","tags":{"Attributes":"private","Environment":"compass","Name":"compass-us-east-1-compass-prod-private","Organization":"FlipsideCrypto","Owner":"DevOps","Stage":"us-east-1","Terraform":"terraform"},"tenant":""},"organization":"FlipsideCrypto","owner":"DevOps","performance_mode":"generalPurpose","private":true,"provisioned_throughput_in_mibps":0,"public":false,"regex_replace_chars":null,"region":null,"security_group_arn":"arn:aws:ec2:us-east-1:957136710666:security-group/sg-0be201a5cae95ebf3","security_group_create_before_destroy":true,"security_group_create_timeout":"10m","security_group_delete_timeout":"15m","security_group_description":"EFS Security Group","security_group_id":"sg-0be201a5cae95ebf3","security_group_name":[],"short_name":"compass-prod","ssm_parameters":["/infrastructure/Compass/efs_filesystems/compass-us-east-1-compass-prod-private/host"],"ssm_path_prefix":"/infrastructure/Compass/efs_filesystems","stage":"us-east-1","subnets":[],"tags":{},"tags_as_list_of_maps":[{"key":"Attributes","value":"private"},{"key":"Environment","value":"compass"},{"key":"Name","value":"compass-us-east-1-compass-prod-private"},{"key":"Organization","value":"FlipsideCrypto"},{"key":"Owner","value":"DevOps"},{"key":"Stage","value":"us-east-1"},{"key":"Terraform","value":"terraform"}],"tenant":null,"terraform":"terraform","throughput_mode":"bursting","traffic":"private","transition_to_ia":["AFTER_90_DAYS"],"transition_to_primary_storage_class":[],"vpc_id":null,"zone_id":["Z05149656FOJW6ACCQF2"]},"compass-us-east-1-compass-stg-private":{"access_point_arns":{},"access_point_ids":{},"access_points":{},"account_id":"957136710666","account_json_key":"Compass","accounts":["Compass"],"additional_security_group_rules":[],"additional_tag_map":{},"allowed_cidr_blocks":[],"allowed_security_group_ids":[],"arn":"arn:aws:elasticfilesystem:us-east-1:957136710666:file-system/fs-0aac20957e92a60b9","associated_security_group_ids":[],"attributes":"private","availability_zone_name":null,"category":"efs_filesystems","context":{"additional_tag_map":{},"attributes":["private"],"delimiter":null,"descriptor_formats":{},"enabled":true,"environment":"compass","id_length_limit":null,"label_key_case":null,"label_order":[],"label_value_case":null,"labels_as_tags":["default"],"name":"compass-stg","namespace":null,"regex_replace_chars":null,"stage":"us-east-1","tags":{"Environment":"compass","Organization":"FlipsideCrypto","Owner":"DevOps","Stage":"us-east-1","Terraform":"terraform"},"tenant":null},"create_security_group":true,"delimiter":null,"descriptor_formats":{},"descriptors":{},"dns_name":"","efs_backup_policy_enabled":true,"efs_cross_account_policy_enabled":false,"enabled":true,"encrypted":true,"environment":"compass","execution_role_arn":"arn:aws:iam::957136710666:role/AWSControlTowerExecution","host":"compass-stg-efs-filesystems-private.flompass.pizza","id":"fs-0aac20957e92a60b9","id_full":"compass-us-east-1-compass-stg-private","id_length_limit":null,"kms_key_id":null,"label_order":[],"mount_target_dns_names":["us-east-1a.fs-0aac20957e92a60b9.efs.us-east-1.amazonaws.com","us-east-1b.fs-0aac20957e92a60b9.efs.us-east-1.amazonaws.com","us-east-1c.fs-0aac20957e92a60b9.efs.us-east-1.amazonaws.com"],"mount_target_ids":["fsmt-044ef90957e192545","fsmt-0a3f2454dd19f610e","fsmt-075a5a4bd7aa59ec6"],"mount_target_ip_address":null,"mount_target_ips":["172.25.6.134","172.25.31.71","172.25.34.13"],"name":"compass-us-east-1-compass-stg-private","namespace":null,"network_interface_ids":["eni-08f2c9432d2c6f6ae","eni-05a0e06300d8c1c2a","eni-0b805cce1cfcc7852"],"network_map":{"Compass":"cluster_Compass"},"normalized_context":{"additional_tag_map":{},"attributes":["private"],"delimiter":"-","descriptor_formats":{},"enabled":true,"environment":"compass","id_length_limit":0,"label_key_case":"title","label_order":["namespace","environment","stage","name","attributes"],"label_value_case":"lower","labels_as_tags":["attributes","environment","name","namespace","stage","tenant"],"name":"compass-stg","namespace":"","regex_replace_chars":"/[^-a-zA-Z0-9]/","stage":"us-east-1","tags":{"Attributes":"private","Environment":"compass","Name":"compass-us-east-1-compass-stg-private","Organization":"FlipsideCrypto","Owner":"DevOps","Stage":"us-east-1","Terraform":"terraform"},"tenant":""},"organization":"FlipsideCrypto","owner":"DevOps","performance_mode":"generalPurpose","private":true,"provisioned_throughput_in_mibps":0,"public":false,"regex_replace_chars":null,"region":null,"security_group_arn":"arn:aws:ec2:us-east-1:957136710666:security-group/sg-0fe1920405b4383f3","security_group_create_before_destroy":true,"security_group_create_timeout":"10m","security_group_delete_timeout":"15m","security_group_description":"EFS Security Group","security_group_id":"sg-0fe1920405b4383f3","security_group_name":[],"short_name":"compass-stg","ssm_parameters":["/infrastructure/Compass/efs_filesystems/compass-us-east-1-compass-stg-private/host"],"ssm_path_prefix":"/infrastructure/Compass/efs_filesystems","stage":"us-east-1","subnets":[],"tags":{},"tags_as_list_of_maps":[{"key":"Attributes","value":"private"},{"key":"Environment","value":"compass"},{"key":"Name","value":"compass-us-east-1-compass-stg-private"},{"key":"Organization","value":"FlipsideCrypto"},{"key":"Owner","value":"DevOps"},{"key":"Stage","value":"us-east-1"},{"key":"Terraform","value":"terraform"}],"tenant":null,"terraform":"terraform","throughput_mode":"bursting","traffic":"private","transition_to_ia":["AFTER_90_DAYS"],"transition_to_primary_storage_class":[],"vpc_id":null,"zone_id":["Z05149656FOJW6ACCQF2"]}},"s3_buckets":{"compass-us-east-1-fsc-analytics-private":{"access_key_enabled":true,"access_key_id":null,"access_key_id_ssm_path":null,"account_id":"957136710666","account_json_key":"Compass","accounts":["Compass"],"acl":"private","additional_tag_map":{},"allow_encrypted_uploads_only":false,"allow_ssl_requests_only":false,"allowed_bucket_actions":["s3:PutObject"],"attributes":"private","block_public_acls":true,"block_public_policy":true,"bucket_arn":"arn:aws:s3:::compass-us-east-1-fsc-analytics-private","bucket_domain_name":"compass-us-east-1-fsc-analytics-private.s3.amazonaws.com","bucket_id":"compass-us-east-1-fsc-analytics-private","bucket_key_enabled":false,"bucket_name":null,"bucket_region":"us-east-1","bucket_regional_domain_name":"compass-us-east-1-fsc-analytics-private.s3.amazonaws.com","bucket_website_domain":"","bucket_website_endpoint":"","category":"s3_buckets","context":{"additional_tag_map":{},"attributes":["private"],"delimiter":null,"descriptor_formats":{},"enabled":true,"environment":"compass","id_length_limit":null,"label_key_case":null,"label_order":[],"label_value_case":null,"labels_as_tags":["default"],"name":"fsc-analytics","namespace":null,"regex_replace_chars":null,"stage":"us-east-1","tags":{"Environment":"compass","Organization":"FlipsideCrypto","Owner":"DevOps","Stage":"us-east-1","Terraform":"terraform"},"tenant":null},"cors_configuration":[],"delimiter":null,"delivery_stream":true,"delivery_stream_arn":"arn:aws:firehose:us-east-1:957136710666:deliverystream/compass-us-east-1-fsc-analytics-private","delivery_stream_name":"compass-us-east-1-fsc-analytics-private","descriptor_formats":{},"descriptors":{},"enabled":true,"environment":"compass","execution_role_arn":"arn:aws:iam::957136710666:role/AWSControlTowerExecution","extra_grants":{},"force_destroy":false,"grant_organization_access":true,"grants":[],"id":"compass-us-east-1-fsc-analytics-private","id_full":"compass-us-east-1-fsc-analytics-private","id_length_limit":null,"ignore_public_acls":true,"kms_master_key_arn":"","label_order":[],"logging":null,"managed":true,"max_days":0,"max_noncurrent_days":0,"max_noncurrent_versions":1,"name":"compass-us-east-1-fsc-analytics-private","namespace":null,"network_map":{},"noncurrent_transition_after":0,"noncurrent_transition_to":"","normalized_context":{"additional_tag_map":{},"attributes":["private"],"delimiter":"-","descriptor_formats":{},"enabled":true,"environment":"compass","id_length_limit":0,"label_key_case":"title","label_order":["namespace","environment","stage","name","attributes"],"label_value_case":"lower","labels_as_tags":["attributes","environment","name","namespace","stage","tenant"],"name":"fsc-analytics","namespace":"","regex_replace_chars":"/[^-a-zA-Z0-9]/","stage":"us-east-1","tags":{"Attributes":"private","Environment":"compass","Name":"compass-us-east-1-fsc-analytics-private","Organization":"FlipsideCrypto","Owner":"DevOps","Stage":"us-east-1","Terraform":"terraform"},"tenant":""},"object_lock_configuration":null,"organization":"FlipsideCrypto","owner":"DevOps","private":true,"privileged_principal_actions":[],"privileged_principal_arns":[],"public":false,"regex_replace_chars":null,"replication_role_arn":"","restrict_public_buckets":true,"s3_object_ownership":"ObjectWriter","s3_replica_bucket_arn":"","s3_replication_enabled":false,"s3_replication_rules":[],"s3_replication_source_roles":[],"secret_access_key":"","secret_access_key_ssm_path":null,"short_name":"fsc-analytics","skip_grants":false,"source_policy_documents":[],"sse_algorithm":"aws:kms","ssm_base_path":"/s3_user/","ssm_parameters":["/infrastructure/Compass/s3_buckets/compass-us-east-1-fsc-analytics-private/bucket_arn","/infrastructure/Compass/s3_buckets/compass-us-east-1-fsc-analytics-private/bucket_id","/infrastructure/Compass/s3_buckets/compass-us-east-1-fsc-analytics-private/delivery_stream_arn","/infrastructure/Compass/s3_buckets/compass-us-east-1-fsc-analytics-private/delivery_stream_name"],"ssm_path_prefix":"/infrastructure/Compass/s3_buckets","stage":"us-east-1","store_access_key_in_ssm":false,"tags":{},"tags_as_list_of_maps":[{"key":"Attributes","value":"private"},{"key":"Environment","value":"compass"},{"key":"Name","value":"compass-us-east-1-fsc-analytics-private"},{"key":"Organization","value":"FlipsideCrypto"},{"key":"Owner","value":"DevOps"},{"key":"Stage","value":"us-east-1"},{"key":"Terraform","value":"terraform"}],"tenant":null,"terraform":"terraform","traffic":"private","transfer_acceleration_enabled":false,"transition_after":0,"transition_to":"GLACIER","user_arn":"","user_enabled":false,"user_name":"","user_unique_id":"","versioning_enabled":false,"website_configuration":[],"website_redirect_all_requests_to":[]},"fsc-compass-dev":{"access_key_enabled":true,"access_key_id":"AKIA55WOLFQFC4YP37HG","access_key_id_ssm_path":null,"account_id":"957136710666","account_json_key":"Compass","accounts":["Compass"],"acl":"private","additional_tag_map":{},"allow_encrypted_uploads_only":false,"allow_ssl_requests_only":false,"allowed_bucket_actions":["s3:PutObject"],"attributes":"private","block_public_acls":true,"block_public_policy":true,"bucket_arn":"arn:aws:s3:::fsc-compass-dev","bucket_domain_name":"fsc-compass-dev.s3.amazonaws.com","bucket_id":"fsc-compass-dev","bucket_key_enabled":false,"bucket_name":"fsc-compass-dev","bucket_region":"us-east-1","bucket_regional_domain_name":"fsc-compass-dev.s3.amazonaws.com","bucket_website_domain":"","bucket_website_endpoint":"","category":"s3_buckets","context":{"additional_tag_map":{},"attributes":["private"],"delimiter":null,"descriptor_formats":{},"enabled":true,"environment":"compass","id_length_limit":null,"label_key_case":null,"label_order":[],"label_value_case":null,"labels_as_tags":["default"],"name":"fsc-compass-dev","namespace":null,"regex_replace_chars":null,"stage":"us-east-1","tags":{"Environment":"compass","Organization":"FlipsideCrypto","Owner":"DevOps","Stage":"us-east-1","Terraform":"terraform"},"tenant":null},"cors_configuration":[],"delimiter":null,"delivery_stream":false,"delivery_stream_arn":"","delivery_stream_name":"","descriptor_formats":{},"descriptors":{},"enabled":true,"environment":"compass","execution_role_arn":"arn:aws:iam::957136710666:role/AWSControlTowerExecution","extra_grants":{},"force_destroy":false,"grant_organization_access":true,"grants":[],"id":"compass-us-east-1-fsc-compass-dev-private","id_full":"compass-us-east-1-fsc-compass-dev-private","id_length_limit":null,"ignore_public_acls":true,"kms_master_key_arn":"","label_order":[],"logging":null,"managed":true,"max_days":0,"max_noncurrent_days":0,"max_noncurrent_versions":1,"name":"compass-us-east-1-fsc-compass-dev-private","namespace":null,"network_map":{},"noncurrent_transition_after":0,"noncurrent_transition_to":"","normalized_context":{"additional_tag_map":{},"attributes":["private"],"delimiter":"-","descriptor_formats":{},"enabled":true,"environment":"compass","id_length_limit":0,"label_key_case":"title","label_order":["namespace","environment","stage","name","attributes"],"label_value_case":"lower","labels_as_tags":["attributes","environment","name","namespace","stage","tenant"],"name":"fsc-compass-dev","namespace":"","regex_replace_chars":"/[^-a-zA-Z0-9]/","stage":"us-east-1","tags":{"Attributes":"private","Environment":"compass","Name":"compass-us-east-1-fsc-compass-dev-private","Organization":"FlipsideCrypto","Owner":"DevOps","Stage":"us-east-1","Terraform":"terraform"},"tenant":""},"object_lock_configuration":null,"organization":"FlipsideCrypto","owner":"DevOps","private":true,"privileged_principal_actions":[],"privileged_principal_arns":[],"public":false,"regex_replace_chars":null,"replication_role_arn":"","restrict_public_buckets":true,"s3_object_ownership":"ObjectWriter","s3_replica_bucket_arn":"","s3_replication_enabled":false,"s3_replication_rules":[],"s3_replication_source_roles":[],"secret_access_key":"VHyurlhe6/nzwVPTOWXB9XhCJ+9QbeLmUAgn932e","secret_access_key_ssm_path":null,"short_name":"fsc-compass-dev","skip_grants":false,"source_policy_documents":[],"sse_algorithm":"aws:kms","ssm_base_path":"/s3_user/","ssm_parameters":["/infrastructure/Compass/s3_buckets/fsc-compass-dev/bucket_arn","/infrastructure/Compass/s3_buckets/fsc-compass-dev/bucket_id"],"ssm_path_prefix":"/infrastructure/Compass/s3_buckets","stage":"us-east-1","store_access_key_in_ssm":false,"tags":{},"tags_as_list_of_maps":[{"key":"Attributes","value":"private"},{"key":"Environment","value":"compass"},{"key":"Name","value":"compass-us-east-1-fsc-compass-dev-private"},{"key":"Organization","value":"FlipsideCrypto"},{"key":"Owner","value":"DevOps"},{"key":"Stage","value":"us-east-1"},{"key":"Terraform","value":"terraform"}],"tenant":null,"terraform":"terraform","traffic":"private","transfer_acceleration_enabled":false,"transition_after":3,"transition_to":"GLACIER","user_arn":"arn:aws:iam::957136710666:user/compass-us-east-1-fsc-compass-dev-private","user_enabled":true,"user_name":"compass-us-east-1-fsc-compass-dev-private","user_unique_id":"AIDA55WOLFQFDZ347GYU3","versioning_enabled":false,"website_configuration":[],"website_redirect_all_requests_to":[]},"fsc-compass-lambda-artifacts":{"access_key_enabled":true,"access_key_id":"AKIA55WOLFQFKLSKD6QS","access_key_id_ssm_path":null,"account_id":"957136710666","account_json_key":"Compass","accounts":["Compass"],"acl":"private","additional_tag_map":{},"allow_encrypted_uploads_only":false,"allow_ssl_requests_only":false,"allowed_bucket_actions":["s3:PutObject"],"attributes":"private","block_public_acls":true,"block_public_policy":true,"bucket_arn":"arn:aws:s3:::fsc-compass-lambda-artifacts","bucket_domain_name":"fsc-compass-lambda-artifacts.s3.amazonaws.com","bucket_id":"fsc-compass-lambda-artifacts","bucket_key_enabled":false,"bucket_name":"fsc-compass-lambda-artifacts","bucket_region":"us-east-1","bucket_regional_domain_name":"fsc-compass-lambda-artifacts.s3.amazonaws.com","bucket_website_domain":"","bucket_website_endpoint":"","category":"s3_buckets","context":{"additional_tag_map":{},"attributes":["private"],"delimiter":null,"descriptor_formats":{},"enabled":true,"environment":"compass","id_length_limit":null,"label_key_case":null,"label_order":[],"label_value_case":null,"labels_as_tags":["default"],"name":"fsc-compass-lambda-artifacts","namespace":null,"regex_replace_chars":null,"stage":"us-east-1","tags":{"Environment":"compass","Organization":"FlipsideCrypto","Owner":"DevOps","Stage":"us-east-1","Terraform":"terraform"},"tenant":null},"cors_configuration":[],"delimiter":null,"delivery_stream":false,"delivery_stream_arn":"","delivery_stream_name":"","descriptor_formats":{},"descriptors":{},"enabled":true,"environment":"compass","execution_role_arn":"arn:aws:iam::957136710666:role/AWSControlTowerExecution","extra_grants":{},"force_destroy":false,"grant_organization_access":true,"grants":[],"id":"compass-us-east-1-fsc-compass-lambda-artifacts-private","id_full":"compass-us-east-1-fsc-compass-lambda-artifacts-private","id_length_limit":null,"ignore_public_acls":true,"kms_master_key_arn":"","label_order":[],"logging":null,"managed":true,"max_days":0,"max_noncurrent_days":0,"max_noncurrent_versions":1,"name":"compass-us-east-1-fsc-compass-lambda-artifacts-private","namespace":null,"network_map":{},"noncurrent_transition_after":0,"noncurrent_transition_to":"","normalized_context":{"additional_tag_map":{},"attributes":["private"],"delimiter":"-","descriptor_formats":{},"enabled":true,"environment":"compass","id_length_limit":0,"label_key_case":"title","label_order":["namespace","environment","stage","name","attributes"],"label_value_case":"lower","labels_as_tags":["attributes","environment","name","namespace","stage","tenant"],"name":"fsc-compass-lambda-artifacts","namespace":"","regex_replace_chars":"/[^-a-zA-Z0-9]/","stage":"us-east-1","tags":{"Attributes":"private","Environment":"compass","Name":"compass-us-east-1-fsc-compass-lambda-artifacts-private","Organization":"FlipsideCrypto","Owner":"DevOps","Stage":"us-east-1","Terraform":"terraform"},"tenant":""},"object_lock_configuration":null,"organization":"FlipsideCrypto","owner":"DevOps","private":true,"privileged_principal_actions":[],"privileged_principal_arns":[],"public":false,"regex_replace_chars":null,"replication_role_arn":"","restrict_public_buckets":true,"s3_object_ownership":"ObjectWriter","s3_replica_bucket_arn":"","s3_replication_enabled":false,"s3_replication_rules":[],"s3_replication_source_roles":[],"secret_access_key":"uEouTEHsw2IjDLwolZfyOqQX2+PlUDWwfhT5/PAW","secret_access_key_ssm_path":null,"short_name":"fsc-compass-lambda-artifacts","skip_grants":false,"source_policy_documents":[],"sse_algorithm":"aws:kms","ssm_base_path":"/s3_user/","ssm_parameters":["/infrastructure/Compass/s3_buckets/fsc-compass-lambda-artifacts/bucket_arn","/infrastructure/Compass/s3_buckets/fsc-compass-lambda-artifacts/bucket_id"],"ssm_path_prefix":"/infrastructure/Compass/s3_buckets","stage":"us-east-1","store_access_key_in_ssm":false,"tags":{},"tags_as_list_of_maps":[{"key":"Attributes","value":"private"},{"key":"Environment","value":"compass"},{"key":"Name","value":"compass-us-east-1-fsc-compass-lambda-artifacts-private"},{"key":"Organization","value":"FlipsideCrypto"},{"key":"Owner","value":"DevOps"},{"key":"Stage","value":"us-east-1"},{"key":"Terraform","value":"terraform"}],"tenant":null,"terraform":"terraform","traffic":"private","transfer_acceleration_enabled":false,"transition_after":30,"transition_to":"GLACIER","user_arn":"arn:aws:iam::957136710666:user/compass-us-east-1-fsc-compass-lambda-artifacts-private","user_enabled":true,"user_name":"compass-us-east-1-fsc-compass-lambda-artifacts-private","user_unique_id":"AIDA55WOLFQFBO2NFEFNI","versioning_enabled":true,"website_configuration":[],"website_redirect_all_requests_to":[]},"fsc-compass-prod":{"access_key_enabled":true,"access_key_id":"AKIA55WOLFQFOFMZRX5C","access_key_id_ssm_path":null,"account_id":"957136710666","account_json_key":"Compass","accounts":["Compass"],"acl":"private","additional_tag_map":{},"allow_encrypted_uploads_only":false,"allow_ssl_requests_only":false,"allowed_bucket_actions":["s3:PutObject"],"attributes":"private","block_public_acls":true,"block_public_policy":true,"bucket_arn":"arn:aws:s3:::fsc-compass-prod","bucket_domain_name":"fsc-compass-prod.s3.amazonaws.com","bucket_id":"fsc-compass-prod","bucket_key_enabled":false,"bucket_name":"fsc-compass-prod","bucket_region":"us-east-1","bucket_regional_domain_name":"fsc-compass-prod.s3.amazonaws.com","bucket_website_domain":"","bucket_website_endpoint":"","category":"s3_buckets","context":{"additional_tag_map":{},"attributes":["private"],"delimiter":null,"descriptor_formats":{},"enabled":true,"environment":"compass","id_length_limit":null,"label_key_case":null,"label_order":[],"label_value_case":null,"labels_as_tags":["default"],"name":"fsc-compass-prod","namespace":null,"regex_replace_chars":null,"stage":"us-east-1","tags":{"Environment":"compass","Organization":"FlipsideCrypto","Owner":"DevOps","Stage":"us-east-1","Terraform":"terraform"},"tenant":null},"cors_configuration":[],"delimiter":null,"delivery_stream":false,"delivery_stream_arn":"","delivery_stream_name":"","descriptor_formats":{},"descriptors":{},"enabled":true,"environment":"compass","execution_role_arn":"arn:aws:iam::957136710666:role/AWSControlTowerExecution","extra_grants":{},"force_destroy":false,"grant_organization_access":true,"grants":[],"id":"compass-us-east-1-fsc-compass-prod-private","id_full":"compass-us-east-1-fsc-compass-prod-private","id_length_limit":null,"ignore_public_acls":true,"kms_master_key_arn":"","label_order":[],"logging":null,"managed":true,"max_days":0,"max_noncurrent_days":0,"max_noncurrent_versions":1,"name":"compass-us-east-1-fsc-compass-prod-private","namespace":null,"network_map":{},"noncurrent_transition_after":0,"noncurrent_transition_to":"","normalized_context":{"additional_tag_map":{},"attributes":["private"],"delimiter":"-","descriptor_formats":{},"enabled":true,"environment":"compass","id_length_limit":0,"label_key_case":"title","label_order":["namespace","environment","stage","name","attributes"],"label_value_case":"lower","labels_as_tags":["attributes","environment","name","namespace","stage","tenant"],"name":"fsc-compass-prod","namespace":"","regex_replace_chars":"/[^-a-zA-Z0-9]/","stage":"us-east-1","tags":{"Attributes":"private","Environment":"compass","Name":"compass-us-east-1-fsc-compass-prod-private","Organization":"FlipsideCrypto","Owner":"DevOps","Stage":"us-east-1","Terraform":"terraform"},"tenant":""},"object_lock_configuration":null,"organization":"FlipsideCrypto","owner":"DevOps","private":true,"privileged_principal_actions":[],"privileged_principal_arns":[],"public":false,"regex_replace_chars":null,"replication_role_arn":"","restrict_public_buckets":true,"s3_object_ownership":"ObjectWriter","s3_replica_bucket_arn":"","s3_replication_enabled":false,"s3_replication_rules":[],"s3_replication_source_roles":[],"secret_access_key":"f82Dal83yw+ZPY7hnh5+vvk8zi5xT88poz5ZbG9I","secret_access_key_ssm_path":null,"short_name":"fsc-compass-prod","skip_grants":false,"source_policy_documents":[],"sse_algorithm":"aws:kms","ssm_base_path":"/s3_user/","ssm_parameters":["/infrastructure/Compass/s3_buckets/fsc-compass-prod/bucket_arn","/infrastructure/Compass/s3_buckets/fsc-compass-prod/bucket_id"],"ssm_path_prefix":"/infrastructure/Compass/s3_buckets","stage":"us-east-1","store_access_key_in_ssm":false,"tags":{},"tags_as_list_of_maps":[{"key":"Attributes","value":"private"},{"key":"Environment","value":"compass"},{"key":"Name","value":"compass-us-east-1-fsc-compass-prod-private"},{"key":"Organization","value":"FlipsideCrypto"},{"key":"Owner","value":"DevOps"},{"key":"Stage","value":"us-east-1"},{"key":"Terraform","value":"terraform"}],"tenant":null,"terraform":"terraform","traffic":"private","transfer_acceleration_enabled":false,"transition_after":30,"transition_to":"GLACIER","user_arn":"arn:aws:iam::957136710666:user/compass-us-east-1-fsc-compass-prod-private","user_enabled":true,"user_name":"compass-us-east-1-fsc-compass-prod-private","user_unique_id":"AIDA55WOLFQFCAIZXK76K","versioning_enabled":true,"website_configuration":[],"website_redirect_all_requests_to":[]},"fsc-compass-stg":{"access_key_enabled":true,"access_key_id":"AKIA55WOLFQFNJIUVGKK","access_key_id_ssm_path":null,"account_id":"957136710666","account_json_key":"Compass","accounts":["Compass"],"acl":"private","additional_tag_map":{},"allow_encrypted_uploads_only":false,"allow_ssl_requests_only":false,"allowed_bucket_actions":["s3:PutObject"],"attributes":"private","block_public_acls":true,"block_public_policy":true,"bucket_arn":"arn:aws:s3:::fsc-compass-stg","bucket_domain_name":"fsc-compass-stg.s3.amazonaws.com","bucket_id":"fsc-compass-stg","bucket_key_enabled":false,"bucket_name":"fsc-compass-stg","bucket_region":"us-east-1","bucket_regional_domain_name":"fsc-compass-stg.s3.amazonaws.com","bucket_website_domain":"","bucket_website_endpoint":"","category":"s3_buckets","context":{"additional_tag_map":{},"attributes":["private"],"delimiter":null,"descriptor_formats":{},"enabled":true,"environment":"compass","id_length_limit":null,"label_key_case":null,"label_order":[],"label_value_case":null,"labels_as_tags":["default"],"name":"fsc-compass-stg","namespace":null,"regex_replace_chars":null,"stage":"us-east-1","tags":{"Environment":"compass","Organization":"FlipsideCrypto","Owner":"DevOps","Stage":"us-east-1","Terraform":"terraform"},"tenant":null},"cors_configuration":[],"delimiter":null,"delivery_stream":false,"delivery_stream_arn":"","delivery_stream_name":"","descriptor_formats":{},"descriptors":{},"enabled":true,"environment":"compass","execution_role_arn":"arn:aws:iam::957136710666:role/AWSControlTowerExecution","extra_grants":{},"force_destroy":false,"grant_organization_access":true,"grants":[],"id":"compass-us-east-1-fsc-compass-stg-private","id_full":"compass-us-east-1-fsc-compass-stg-private","id_length_limit":null,"ignore_public_acls":true,"kms_master_key_arn":"","label_order":[],"logging":null,"managed":true,"max_days":0,"max_noncurrent_days":0,"max_noncurrent_versions":1,"name":"compass-us-east-1-fsc-compass-stg-private","namespace":null,"network_map":{},"noncurrent_transition_after":0,"noncurrent_transition_to":"","normalized_context":{"additional_tag_map":{},"attributes":["private"],"delimiter":"-","descriptor_formats":{},"enabled":true,"environment":"compass","id_length_limit":0,"label_key_case":"title","label_order":["namespace","environment","stage","name","attributes"],"label_value_case":"lower","labels_as_tags":["attributes","environment","name","namespace","stage","tenant"],"name":"fsc-compass-stg","namespace":"","regex_replace_chars":"/[^-a-zA-Z0-9]/","stage":"us-east-1","tags":{"Attributes":"private","Environment":"compass","Name":"compass-us-east-1-fsc-compass-stg-private","Organization":"FlipsideCrypto","Owner":"DevOps","Stage":"us-east-1","Terraform":"terraform"},"tenant":""},"object_lock_configuration":null,"organization":"FlipsideCrypto","owner":"DevOps","private":true,"privileged_principal_actions":[],"privileged_principal_arns":[],"public":false,"regex_replace_chars":null,"replication_role_arn":"","restrict_public_buckets":true,"s3_object_ownership":"ObjectWriter","s3_replica_bucket_arn":"","s3_replication_enabled":false,"s3_replication_rules":[],"s3_replication_source_roles":[],"secret_access_key":"D9idWwie3fmsd19HbpA6hBLzwJvr3dBAp2l/OLdw","secret_access_key_ssm_path":null,"short_name":"fsc-compass-stg","skip_grants":false,"source_policy_documents":[],"sse_algorithm":"aws:kms","ssm_base_path":"/s3_user/","ssm_parameters":["/infrastructure/Compass/s3_buckets/fsc-compass-stg/bucket_arn","/infrastructure/Compass/s3_buckets/fsc-compass-stg/bucket_id"],"ssm_path_prefix":"/infrastructure/Compass/s3_buckets","stage":"us-east-1","store_access_key_in_ssm":false,"tags":{},"tags_as_list_of_maps":[{"key":"Attributes","value":"private"},{"key":"Environment","value":"compass"},{"key":"Name","value":"compass-us-east-1-fsc-compass-stg-private"},{"key":"Organization","value":"FlipsideCrypto"},{"key":"Owner","value":"DevOps"},{"key":"Stage","value":"us-east-1"},{"key":"Terraform","value":"terraform"}],"tenant":null,"terraform":"terraform","traffic":"private","transfer_acceleration_enabled":false,"transition_after":7,"transition_to":"GLACIER","user_arn":"arn:aws:iam::957136710666:user/compass-us-east-1-fsc-compass-stg-private","user_enabled":true,"user_name":"compass-us-east-1-fsc-compass-stg-private","user_unique_id":"AIDA55WOLFQFKYCXLQ6TN","versioning_enabled":false,"website_configuration":[],"website_redirect_all_requests_to":[]}}},"Data_Platform_Testbed":{"access_logs":{"dataplatformtestbed-access-logs-flipside-crypto":{"bucket_arn":"arn:aws:s3:::dataplatformtestbed-access-logs-flipside-crypto","bucket_domain_name":"dataplatformtestbed-access-logs-flipside-crypto.s3.amazonaws.com","bucket_id":"dataplatformtestbed-access-logs-flipside-crypto","bucket_prefix":"","enabled":true}},"efs_filesystems":{},"s3_buckets":{}},"FlipsideCryptoRoot":{"access_logs":{"flipsidecryptoroot-access-logs-flipside-crypto":{"bucket_arn":"arn:aws:s3:::flipsidecryptoroot-access-logs-flipside-crypto","bucket_domain_name":"flipsidecryptoroot-access-logs-flipside-crypto.s3.amazonaws.com","bucket_id":"flipsidecryptoroot-access-logs-flipside-crypto","bucket_prefix":"","enabled":true}},"efs_filesystems":{"rstudio-prod":{"access_point_arns":{},"access_point_ids":{},"account_json_key":"FlipsideCryptoRoot","arn":"arn:aws:elasticfilesystem:us-east-1:862006574860:file-system/fs-029bf01134c419079","category":"efs_filesystems","dns_name":"fs-029bf01134c419079.efs.us-east-1.amazonaws.com","domain":"flipside.systems","environment":"prod","environments":["stg","prod"],"host":"rstudio-efs.flipside.systems","id":"fs-029bf01134c419079","mount_target_dns_names":["us-east-1c.fs-029bf01134c419079.efs.us-east-1.amazonaws.com","us-east-1a.fs-029bf01134c419079.efs.us-east-1.amazonaws.com","us-east-1b.fs-029bf01134c419079.efs.us-east-1.amazonaws.com"],"mount_target_ids":["fsmt-0c846c5e09e42c145","fsmt-0f750a62d59bd9bc3","fsmt-0c3db9508c6d4e557"],"mount_target_ips":["10.30.32.128","10.30.3.55","10.30.19.116"],"network_interface_ids":["eni-00addb9c47159d7a1","eni-070dde601386d39d2","eni-0ee88bd1db4322560"],"security_group_arn":"arn:aws:ec2:us-east-1:862006574860:security-group/sg-0cfbb21f07023387f","security_group_id":"sg-0cfbb21f07023387f","security_group_name":"rstudio-prod-efs20220325200220915000000002","short_name":"rstudio","ssm_parameters":["/infrastructure/FlipsideCryptoRoot/efs_filesystems/rstudio-prod/dns_name","/infrastructure/FlipsideCryptoRoot/efs_filesystems/rstudio-prod/host"],"ssm_path_prefix":"/infrastructure/FlipsideCryptoRoot/efs_filesystems","tags":{"Environment":"prod","Organization":"FlipsideCrypto","Owner":"DevOps","Stage":"us-east-1","Terraform":"terraform"},"traffic":"private"},"rstudio-stg":{"access_point_arns":{},"access_point_ids":{},"account_json_key":"FlipsideCryptoRoot","arn":"arn:aws:elasticfilesystem:us-east-1:862006574860:file-system/fs-0307504b4f28530e8","category":"efs_filesystems","dns_name":"fs-0307504b4f28530e8.efs.us-east-1.amazonaws.com","domain":"flipside.kitchen","environment":"stg","environments":["stg","prod"],"host":"rstudio-efs.flipside.kitchen","id":"fs-0307504b4f28530e8","mount_target_dns_names":["us-east-1c.fs-0307504b4f28530e8.efs.us-east-1.amazonaws.com","us-east-1a.fs-0307504b4f28530e8.efs.us-east-1.amazonaws.com","us-east-1b.fs-0307504b4f28530e8.efs.us-east-1.amazonaws.com"],"mount_target_ids":["fsmt-0dd555219d5fa850e","fsmt-00469add9c414b09c","fsmt-0557c02cdf5bdf522"],"mount_target_ips":["10.30.34.220","10.30.6.47","10.30.30.62"],"network_interface_ids":["eni-0f1c3444c2ce588ab","eni-0eba27c0aa2fc0b3c","eni-080382902bc5ad8c0"],"security_group_arn":"arn:aws:ec2:us-east-1:862006574860:security-group/sg-01bd68526a22e425a","security_group_id":"sg-01bd68526a22e425a","security_group_name":"rstudio-stg-efs20221031191554988200000001","short_name":"rstudio","ssm_parameters":["/infrastructure/FlipsideCryptoRoot/efs_filesystems/rstudio-stg/dns_name","/infrastructure/FlipsideCryptoRoot/efs_filesystems/rstudio-stg/host"],"ssm_path_prefix":"/infrastructure/FlipsideCryptoRoot/efs_filesystems","tags":{"Environment":"stg","Organization":"FlipsideCrypto","Owner":"DevOps","Stage":"us-east-1","Terraform":"terraform"},"traffic":"private"}},"s3_buckets":{"fsc-chainwalkers-exported-data":{"access_key_enabled":true,"access_key_id":"","access_key_id_ssm_path":"","account_id":"862006574860","account_json_key":"FlipsideCryptoRoot","accounts":["FlipsideCryptoRoot","FlipsideCryptoRoot"],"acl":"private","additional_tag_map":{},"allow_encrypted_uploads_only":false,"allow_ssl_requests_only":false,"allowed_bucket_actions":["s3:PutObject","s3:PutObject"],"attributes":[],"block_public_acls":true,"block_public_policy":true,"bucket_arn":"arn:aws:s3:::fsc-chainwalkers-exported-data","bucket_domain_name":"fsc-chainwalkers-exported-data.s3.amazonaws.com","bucket_id":"fsc-chainwalkers-exported-data","bucket_key_enabled":false,"bucket_name":null,"bucket_region":"us-east-1","bucket_regional_domain_name":"fsc-chainwalkers-exported-data.s3.amazonaws.com","bucket_website_domain":"","bucket_website_endpoint":"","category":"s3_buckets","context":{"additional_tag_map":{},"attributes":["private"],"delimiter":null,"descriptor_formats":{},"enabled":false,"environment":"global","id_length_limit":null,"label_key_case":null,"label_order":[],"label_value_case":null,"labels_as_tags":["default"],"name":"fsc-chainwalkers-exported-data","namespace":null,"regex_replace_chars":null,"stage":"us-east-1","tags":{"Environment":"global","Organization":"FlipsideCrypto","Owner":"DevOps","Stage":"us-east-1","Terraform":"terraform"},"tenant":null},"cors_configuration":[],"delimiter":null,"delivery_stream":false,"delivery_stream_arn":"","delivery_stream_name":"","descriptor_formats":{},"descriptors":{},"enabled":true,"environment":null,"execution_role_arn":"","extra_grants":{},"force_destroy":false,"grant_organization_access":true,"grants":[],"id":"","id_full":"","id_length_limit":null,"ignore_public_acls":true,"kms_master_key_arn":"","label_order":[],"logging":null,"managed":false,"max_days":0,"max_noncurrent_days":0,"max_noncurrent_versions":1,"name":"fsc-chainwalkers-exported-data","namespace":null,"network_map":{},"noncurrent_transition_after":0,"noncurrent_transition_to":"","normalized_context":{"additional_tag_map":{},"attributes":["private"],"delimiter":"-","descriptor_formats":{},"enabled":false,"environment":"global","id_length_limit":0,"label_key_case":"title","label_order":["namespace","environment","stage","name","attributes"],"label_value_case":"lower","labels_as_tags":["attributes","environment","name","namespace","stage","tenant"],"name":"fsc-chainwalkers-exported-data","namespace":"","regex_replace_chars":"/[^-a-zA-Z0-9]/","stage":"us-east-1","tags":{"Attributes":"private","Environment":"global","Name":"global-us-east-1-fsc-chainwalkers-exported-data-private","Organization":"FlipsideCrypto","Owner":"DevOps","Stage":"us-east-1","Terraform":"terraform"},"tenant":""},"object_lock_configuration":null,"private":true,"privileged_principal_actions":[],"privileged_principal_arns":[],"public":false,"regex_replace_chars":null,"replication_role_arn":"","restrict_public_buckets":true,"s3_object_ownership":"ObjectWriter","s3_replica_bucket_arn":"","s3_replication_enabled":false,"s3_replication_rules":[],"s3_replication_source_roles":[],"secret_access_key":"","secret_access_key_ssm_path":"","short_name":"fsc-chainwalkers-exported-data","skip_grants":false,"source_policy_documents":[],"sse_algorithm":"aws:kms","ssm_base_path":"/s3_user/","ssm_parameters":["/infrastructure/FlipsideCryptoRoot/s3_buckets/fsc-chainwalkers-exported-data/bucket_arn","/infrastructure/FlipsideCryptoRoot/s3_buckets/fsc-chainwalkers-exported-data/bucket_id"],"ssm_path_prefix":"/infrastructure/FlipsideCryptoRoot/s3_buckets","stage":null,"store_access_key_in_ssm":false,"tags":{},"tags_as_list_of_maps":[{"key":"Attributes","value":"private"},{"key":"Environment","value":"global"},{"key":"Name","value":"global-us-east-1-fsc-chainwalkers-exported-data-private"},{"key":"Organization","value":"FlipsideCrypto"},{"key":"Owner","value":"DevOps"},{"key":"Stage","value":"us-east-1"},{"key":"Terraform","value":"terraform"}],"tenant":null,"traffic":"private","transfer_acceleration_enabled":false,"transition_after":0,"transition_to":"GLACIER","user_arn":"","user_enabled":false,"user_name":"","user_unique_id":"","versioning_enabled":false,"website_configuration":[],"website_redirect_all_requests_to":[]},"fsc-sf-experiment":{"access_key_enabled":true,"access_key_id":"","access_key_id_ssm_path":"","account_id":"862006574860","account_json_key":"FlipsideCryptoRoot","accounts":["FlipsideCryptoRoot","FlipsideCryptoRoot"],"acl":"private","additional_tag_map":{},"allow_encrypted_uploads_only":false,"allow_ssl_requests_only":false,"allowed_bucket_actions":["s3:PutObject","s3:PutObject"],"attributes":[],"block_public_acls":true,"block_public_policy":true,"bucket_arn":"arn:aws:s3:::fsc-sf-experiment","bucket_domain_name":"fsc-sf-experiment.s3.amazonaws.com","bucket_id":"fsc-sf-experiment","bucket_key_enabled":false,"bucket_name":null,"bucket_region":"us-east-1","bucket_regional_domain_name":"fsc-sf-experiment.s3.amazonaws.com","bucket_website_domain":"","bucket_website_endpoint":"","category":"s3_buckets","context":{"additional_tag_map":{},"attributes":["private"],"delimiter":null,"descriptor_formats":{},"enabled":false,"environment":"global","id_length_limit":null,"label_key_case":null,"label_order":[],"label_value_case":null,"labels_as_tags":["default"],"name":"fsc-sf-experiment","namespace":null,"regex_replace_chars":null,"stage":"us-east-1","tags":{"Environment":"global","Organization":"FlipsideCrypto","Owner":"DevOps","Stage":"us-east-1","Terraform":"terraform"},"tenant":null},"cors_configuration":[],"delimiter":null,"delivery_stream":false,"delivery_stream_arn":"","delivery_stream_name":"","descriptor_formats":{},"descriptors":{},"enabled":true,"environment":null,"execution_role_arn":"","extra_grants":{},"force_destroy":false,"grant_organization_access":true,"grants":[],"id":"","id_full":"","id_length_limit":null,"ignore_public_acls":true,"kms_master_key_arn":"","label_order":[],"logging":null,"managed":false,"max_days":1,"max_noncurrent_days":0,"max_noncurrent_versions":0,"name":"fsc-sf-experiment","namespace":null,"network_map":{},"noncurrent_transition_after":0,"noncurrent_transition_to":"","normalized_context":{"additional_tag_map":{},"attributes":["private"],"delimiter":"-","descriptor_formats":{},"enabled":false,"environment":"global","id_length_limit":0,"label_key_case":"title","label_order":["namespace","environment","stage","name","attributes"],"label_value_case":"lower","labels_as_tags":["attributes","environment","name","namespace","stage","tenant"],"name":"fsc-sf-experiment","namespace":"","regex_replace_chars":"/[^-a-zA-Z0-9]/","stage":"us-east-1","tags":{"Attributes":"private","Environment":"global","Name":"global-us-east-1-fsc-sf-experiment-private","Organization":"FlipsideCrypto","Owner":"DevOps","Stage":"us-east-1","Terraform":"terraform"},"tenant":""},"object_lock_configuration":null,"private":true,"privileged_principal_actions":[],"privileged_principal_arns":[],"public":false,"regex_replace_chars":null,"replication_role_arn":"","restrict_public_buckets":true,"s3_object_ownership":"ObjectWriter","s3_replica_bucket_arn":"","s3_replication_enabled":false,"s3_replication_rules":[],"s3_replication_source_roles":[],"secret_access_key":"","secret_access_key_ssm_path":"","short_name":"fsc-sf-experiment","skip_grants":false,"source_policy_documents":[],"sse_algorithm":"aws:kms","ssm_base_path":"/s3_user/","ssm_parameters":["/infrastructure/FlipsideCryptoRoot/s3_buckets/fsc-sf-experiment/bucket_arn","/infrastructure/FlipsideCryptoRoot/s3_buckets/fsc-sf-experiment/bucket_id"],"ssm_path_prefix":"/infrastructure/FlipsideCryptoRoot/s3_buckets","stage":null,"store_access_key_in_ssm":false,"tags":{},"tags_as_list_of_maps":[{"key":"Attributes","value":"private"},{"key":"Environment","value":"global"},{"key":"Name","value":"global-us-east-1-fsc-sf-experiment-private"},{"key":"Organization","value":"FlipsideCrypto"},{"key":"Owner","value":"DevOps"},{"key":"Stage","value":"us-east-1"},{"key":"Terraform","value":"terraform"}],"tenant":null,"traffic":"private","transfer_acceleration_enabled":false,"transition_after":0,"transition_to":"GLACIER","user_arn":"","user_enabled":false,"user_name":"","user_unique_id":"","versioning_enabled":false,"website_configuration":[],"website_redirect_all_requests_to":[]},"fsc-snowflake":{"access_key_enabled":true,"access_key_id":"","access_key_id_ssm_path":"","account_id":"862006574860","account_json_key":"FlipsideCryptoRoot","accounts":["FlipsideCryptoRoot","FlipsideCryptoRoot"],"acl":"private","additional_tag_map":{},"allow_encrypted_uploads_only":false,"allow_ssl_requests_only":false,"allowed_bucket_actions":["s3:PutObject","s3:PutObject"],"attributes":[],"block_public_acls":true,"block_public_policy":true,"bucket_arn":"arn:aws:s3:::fsc-snowflake","bucket_domain_name":"fsc-snowflake.s3.amazonaws.com","bucket_id":"fsc-snowflake","bucket_key_enabled":false,"bucket_name":null,"bucket_region":"us-east-1","bucket_regional_domain_name":"fsc-snowflake.s3.amazonaws.com","bucket_website_domain":"","bucket_website_endpoint":"","category":"s3_buckets","context":{"additional_tag_map":{},"attributes":["private"],"delimiter":null,"descriptor_formats":{},"enabled":false,"environment":"global","id_length_limit":null,"label_key_case":null,"label_order":[],"label_value_case":null,"labels_as_tags":["default"],"name":"fsc-snowflake","namespace":null,"regex_replace_chars":null,"stage":"us-east-1","tags":{"Environment":"global","Organization":"FlipsideCrypto","Owner":"DevOps","Stage":"us-east-1","Terraform":"terraform"},"tenant":null},"cors_configuration":[],"delimiter":null,"delivery_stream":false,"delivery_stream_arn":"","delivery_stream_name":"","descriptor_formats":{},"descriptors":{},"enabled":true,"environment":null,"execution_role_arn":"","extra_grants":{},"force_destroy":false,"grant_organization_access":true,"grants":[],"id":"","id_full":"","id_length_limit":null,"ignore_public_acls":true,"kms_master_key_arn":"","label_order":[],"logging":null,"managed":false,"max_days":0,"max_noncurrent_days":0,"max_noncurrent_versions":1,"name":"fsc-snowflake","namespace":null,"network_map":{},"noncurrent_transition_after":0,"noncurrent_transition_to":"","normalized_context":{"additional_tag_map":{},"attributes":["private"],"delimiter":"-","descriptor_formats":{},"enabled":false,"environment":"global","id_length_limit":0,"label_key_case":"title","label_order":["namespace","environment","stage","name","attributes"],"label_value_case":"lower","labels_as_tags":["attributes","environment","name","namespace","stage","tenant"],"name":"fsc-snowflake","namespace":"","regex_replace_chars":"/[^-a-zA-Z0-9]/","stage":"us-east-1","tags":{"Attributes":"private","Environment":"global","Name":"global-us-east-1-fsc-snowflake-private","Organization":"FlipsideCrypto","Owner":"DevOps","Stage":"us-east-1","Terraform":"terraform"},"tenant":""},"object_lock_configuration":null,"private":true,"privileged_principal_actions":[],"privileged_principal_arns":[],"public":false,"regex_replace_chars":null,"replication_role_arn":"","restrict_public_buckets":true,"s3_object_ownership":"ObjectWriter","s3_replica_bucket_arn":"","s3_replication_enabled":false,"s3_replication_rules":[],"s3_replication_source_roles":[],"secret_access_key":"","secret_access_key_ssm_path":"","short_name":"fsc-snowflake","skip_grants":false,"source_policy_documents":[],"sse_algorithm":"aws:kms","ssm_base_path":"/s3_user/","ssm_parameters":["/infrastructure/FlipsideCryptoRoot/s3_buckets/fsc-snowflake/bucket_arn","/infrastructure/FlipsideCryptoRoot/s3_buckets/fsc-snowflake/bucket_id"],"ssm_path_prefix":"/infrastructure/FlipsideCryptoRoot/s3_buckets","stage":null,"store_access_key_in_ssm":false,"tags":{},"tags_as_list_of_maps":[{"key":"Attributes","value":"private"},{"key":"Environment","value":"global"},{"key":"Name","value":"global-us-east-1-fsc-snowflake-private"},{"key":"Organization","value":"FlipsideCrypto"},{"key":"Owner","value":"DevOps"},{"key":"Stage","value":"us-east-1"},{"key":"Terraform","value":"terraform"}],"tenant":null,"traffic":"private","transfer_acceleration_enabled":false,"transition_after":0,"transition_to":"GLACIER","user_arn":"","user_enabled":false,"user_name":"","user_unique_id":"","versioning_enabled":false,"website_configuration":[],"website_redirect_all_requests_to":[]}}},"Indexers":{"access_logs":{"indexers-access-logs-flipside-crypto":{"bucket_arn":"arn:aws:s3:::indexers-access-logs-flipside-crypto","bucket_domain_name":"indexers-access-logs-flipside-crypto.s3.amazonaws.com","bucket_id":"indexers-access-logs-flipside-crypto","bucket_prefix":"","enabled":true}},"efs_filesystems":{},"s3_buckets":{}},"Product_Eng_Testbed":{"access_logs":{"productengtestbed-access-logs-flipside-crypto":{"bucket_arn":"arn:aws:s3:::productengtestbed-access-logs-flipside-crypto","bucket_domain_name":"productengtestbed-access-logs-flipside-crypto.s3.amazonaws.com","bucket_id":"productengtestbed-access-logs-flipside-crypto","bucket_prefix":"","enabled":true}},"efs_filesystems":{},"s3_buckets":{}},"Production":{"access_logs":{"production-access-logs-flipside-crypto":{"bucket_arn":"arn:aws:s3:::production-access-logs-flipside-crypto","bucket_domain_name":"production-access-logs-flipside-crypto.s3.amazonaws.com","bucket_id":"production-access-logs-flipside-crypto","bucket_prefix":"","enabled":true}},"efs_filesystems":{},"s3_buckets":{}},"Serverless_Prod":{"access_logs":{"serverlessprod-access-logs-flipside-crypto":{"bucket_arn":"arn:aws:s3:::serverlessprod-access-logs-flipside-crypto","bucket_domain_name":"serverlessprod-access-logs-flipside-crypto.s3.amazonaws.com","bucket_id":"serverlessprod-access-logs-flipside-crypto","bucket_prefix":"","enabled":true}},"efs_filesystems":{},"s3_buckets":{"prod-us-east-1-serverless-near-lake-mainnet-fsc":{"access_key_enabled":true,"access_key_id":null,"access_key_id_ssm_path":null,"account_id":"924682671219","account_json_key":"Serverless_Prod","accounts":["Serverless_Stg","Serverless_Prod"],"acl":"private","additional_tag_map":{},"allow_encrypted_uploads_only":false,"allow_ssl_requests_only":false,"allowed_bucket_actions":["s3:PutObject"],"attributes":"private","block_public_acls":true,"block_public_policy":true,"bucket_arn":"arn:aws:s3:::prod-us-east-1-serverless-near-lake-mainnet-fsc","bucket_domain_name":"prod-us-east-1-serverless-near-lake-mainnet-fsc.s3.amazonaws.com","bucket_id":"prod-us-east-1-serverless-near-lake-mainnet-fsc","bucket_key_enabled":false,"bucket_name":null,"bucket_region":"us-east-1","bucket_regional_domain_name":"prod-us-east-1-serverless-near-lake-mainnet-fsc.s3.amazonaws.com","bucket_website_domain":"","bucket_website_endpoint":"","category":"s3_buckets","context":{"additional_tag_map":{},"attributes":["private"],"delimiter":null,"descriptor_formats":{},"enabled":true,"environment":"prod","id_length_limit":64,"label_key_case":null,"label_order":["environment","stage","name"],"label_value_case":null,"labels_as_tags":["default"],"name":"serverless-near-lake-mainnet-fsc","namespace":null,"regex_replace_chars":null,"stage":"us-east-1","tags":{"Environment":"prod","Organization":"FlipsideCrypto","Owner":"DevOps","Stage":"us-east-1","Terraform":"terraform"},"tenant":null},"cors_configuration":[],"delimiter":null,"delivery_stream":false,"delivery_stream_arn":"","delivery_stream_name":"","descriptor_formats":{},"descriptors":{},"enabled":true,"environment":"prod","execution_role_arn":"arn:aws:iam::924682671219:role/AWSControlTowerExecution","extra_grants":{},"force_destroy":false,"grant_organization_access":true,"grants":[],"id":"prod-us-east-1-serverless-near-lake-mainnet-fsc","id_full":"prod-us-east-1-serverless-near-lake-mainnet-fsc","id_length_limit":64,"ignore_public_acls":true,"kms_master_key_arn":"","label_order":["environment","stage","name"],"logging":null,"managed":true,"max_days":0,"max_noncurrent_days":0,"max_noncurrent_versions":1,"name":"prod-us-east-1-serverless-near-lake-mainnet-fsc","namespace":null,"network_map":{},"noncurrent_transition_after":0,"noncurrent_transition_to":"","normalized_context":{"additional_tag_map":{},"attributes":["private"],"delimiter":"-","descriptor_formats":{},"enabled":true,"environment":"prod","id_length_limit":64,"label_key_case":"title","label_order":["environment","stage","name"],"label_value_case":"lower","labels_as_tags":["attributes","environment","name","namespace","stage","tenant"],"name":"serverless-near-lake-mainnet-fsc","namespace":"","regex_replace_chars":"/[^-a-zA-Z0-9]/","stage":"us-east-1","tags":{"Attributes":"private","Environment":"prod","Name":"prod-us-east-1-serverless-near-lake-mainnet-fsc","Organization":"FlipsideCrypto","Owner":"DevOps","Stage":"us-east-1","Terraform":"terraform"},"tenant":""},"object_lock_configuration":null,"organization":"FlipsideCrypto","owner":"DevOps","private":true,"privileged_principal_actions":[],"privileged_principal_arns":[],"public":false,"regex_replace_chars":null,"replication_role_arn":"","restrict_public_buckets":true,"s3_object_ownership":"ObjectWriter","s3_replica_bucket_arn":"","s3_replication_enabled":false,"s3_replication_rules":[],"s3_replication_source_roles":[],"secret_access_key":"","secret_access_key_ssm_path":null,"short_name":"serverless-near-lake-mainnet-fsc","skip_grants":false,"source_policy_documents":[],"sse_algorithm":"aws:kms","ssm_base_path":"/s3_user/","ssm_parameters":["/infrastructure/Serverless_Prod/s3_buckets/prod-us-east-1-serverless-near-lake-mainnet-fsc/bucket_arn","/infrastructure/Serverless_Prod/s3_buckets/prod-us-east-1-serverless-near-lake-mainnet-fsc/bucket_id"],"ssm_path_prefix":"/infrastructure/Serverless_Prod/s3_buckets","stage":"us-east-1","store_access_key_in_ssm":false,"tags":{},"tags_as_list_of_maps":[{"key":"Attributes","value":"private"},{"key":"Environment","value":"prod"},{"key":"Name","value":"prod-us-east-1-serverless-near-lake-mainnet-fsc"},{"key":"Organization","value":"FlipsideCrypto"},{"key":"Owner","value":"DevOps"},{"key":"Stage","value":"us-east-1"},{"key":"Terraform","value":"terraform"}],"tenant":null,"terraform":"terraform","traffic":"private","transfer_acceleration_enabled":false,"transition_after":0,"transition_to":"GLACIER","user_arn":"","user_enabled":false,"user_name":"","user_unique_id":"","versioning_enabled":false,"website_configuration":[],"website_redirect_all_requests_to":[]}}},"Serverless_Stg":{"access_logs":{"serverlessstg-access-logs-flipside-crypto":{"bucket_arn":"arn:aws:s3:::serverlessstg-access-logs-flipside-crypto","bucket_domain_name":"serverlessstg-access-logs-flipside-crypto.s3.amazonaws.com","bucket_id":"serverlessstg-access-logs-flipside-crypto","bucket_prefix":"","enabled":true}},"efs_filesystems":{},"s3_buckets":{"stg-us-east-1-serverless-near-lake-mainnet-fsc":{"access_key_enabled":true,"access_key_id":null,"access_key_id_ssm_path":null,"account_id":"704693948482","account_json_key":"Serverless_Stg","accounts":["Serverless_Stg","Serverless_Prod"],"acl":"private","additional_tag_map":{},"allow_encrypted_uploads_only":false,"allow_ssl_requests_only":false,"allowed_bucket_actions":["s3:PutObject"],"attributes":"private","block_public_acls":true,"block_public_policy":true,"bucket_arn":"arn:aws:s3:::stg-us-east-1-serverless-near-lake-mainnet-fsc","bucket_domain_name":"stg-us-east-1-serverless-near-lake-mainnet-fsc.s3.amazonaws.com","bucket_id":"stg-us-east-1-serverless-near-lake-mainnet-fsc","bucket_key_enabled":false,"bucket_name":null,"bucket_region":"us-east-1","bucket_regional_domain_name":"stg-us-east-1-serverless-near-lake-mainnet-fsc.s3.amazonaws.com","bucket_website_domain":"","bucket_website_endpoint":"","category":"s3_buckets","context":{"additional_tag_map":{},"attributes":["private"],"delimiter":null,"descriptor_formats":{},"enabled":true,"environment":"stg","id_length_limit":64,"label_key_case":null,"label_order":["environment","stage","name"],"label_value_case":null,"labels_as_tags":["default"],"name":"serverless-near-lake-mainnet-fsc","namespace":null,"regex_replace_chars":null,"stage":"us-east-1","tags":{"Environment":"stg","Organization":"FlipsideCrypto","Owner":"DevOps","Stage":"us-east-1","Terraform":"terraform"},"tenant":null},"cors_configuration":[],"delimiter":null,"delivery_stream":false,"delivery_stream_arn":"","delivery_stream_name":"","descriptor_formats":{},"descriptors":{},"enabled":true,"environment":"stg","execution_role_arn":"arn:aws:iam::704693948482:role/AWSControlTowerExecution","extra_grants":{},"force_destroy":false,"grant_organization_access":true,"grants":[],"id":"stg-us-east-1-serverless-near-lake-mainnet-fsc","id_full":"stg-us-east-1-serverless-near-lake-mainnet-fsc","id_length_limit":64,"ignore_public_acls":true,"kms_master_key_arn":"","label_order":["environment","stage","name"],"logging":null,"managed":true,"max_days":0,"max_noncurrent_days":0,"max_noncurrent_versions":1,"name":"stg-us-east-1-serverless-near-lake-mainnet-fsc","namespace":null,"network_map":{},"noncurrent_transition_after":0,"noncurrent_transition_to":"","normalized_context":{"additional_tag_map":{},"attributes":["private"],"delimiter":"-","descriptor_formats":{},"enabled":true,"environment":"stg","id_length_limit":64,"label_key_case":"title","label_order":["environment","stage","name"],"label_value_case":"lower","labels_as_tags":["attributes","environment","name","namespace","stage","tenant"],"name":"serverless-near-lake-mainnet-fsc","namespace":"","regex_replace_chars":"/[^-a-zA-Z0-9]/","stage":"us-east-1","tags":{"Attributes":"private","Environment":"stg","Name":"stg-us-east-1-serverless-near-lake-mainnet-fsc","Organization":"FlipsideCrypto","Owner":"DevOps","Stage":"us-east-1","Terraform":"terraform"},"tenant":""},"object_lock_configuration":null,"organization":"FlipsideCrypto","owner":"DevOps","private":true,"privileged_principal_actions":[],"privileged_principal_arns":[],"public":false,"regex_replace_chars":null,"replication_role_arn":"","restrict_public_buckets":true,"s3_object_ownership":"ObjectWriter","s3_replica_bucket_arn":"","s3_replication_enabled":false,"s3_replication_rules":[],"s3_replication_source_roles":[],"secret_access_key":"","secret_access_key_ssm_path":null,"short_name":"serverless-near-lake-mainnet-fsc","skip_grants":false,"source_policy_documents":[],"sse_algorithm":"aws:kms","ssm_base_path":"/s3_user/","ssm_parameters":["/infrastructure/Serverless_Stg/s3_buckets/stg-us-east-1-serverless-near-lake-mainnet-fsc/bucket_arn","/infrastructure/Serverless_Stg/s3_buckets/stg-us-east-1-serverless-near-lake-mainnet-fsc/bucket_id"],"ssm_path_prefix":"/infrastructure/Serverless_Stg/s3_buckets","stage":"us-east-1","store_access_key_in_ssm":false,"tags":{},"tags_as_list_of_maps":[{"key":"Attributes","value":"private"},{"key":"Environment","value":"stg"},{"key":"Name","value":"stg-us-east-1-serverless-near-lake-mainnet-fsc"},{"key":"Organization","value":"FlipsideCrypto"},{"key":"Owner","value":"DevOps"},{"key":"Stage","value":"us-east-1"},{"key":"Terraform","value":"terraform"}],"tenant":null,"terraform":"terraform","traffic":"private","transfer_acceleration_enabled":false,"transition_after":0,"transition_to":"GLACIER","user_arn":"","user_enabled":false,"user_name":"","user_unique_id":"","versioning_enabled":false,"website_configuration":[],"website_redirect_all_requests_to":[]}}},"Staging":{"access_logs":{"staging-access-logs-flipside-crypto":{"bucket_arn":"arn:aws:s3:::staging-access-logs-flipside-crypto","bucket_domain_name":"staging-access-logs-flipside-crypto.s3.amazonaws.com","bucket_id":"staging-access-logs-flipside-crypto","bucket_prefix":"","enabled":true}},"efs_filesystems":{},"s3_buckets":{}},"Transit":{"access_logs":{"transit-access-logs-flipside-crypto":{"bucket_arn":"arn:aws:s3:::transit-access-logs-flipside-crypto","bucket_domain_name":"transit-access-logs-flipside-crypto.s3.amazonaws.com","bucket_id":"transit-access-logs-flipside-crypto","bucket_prefix":"","enabled":true}},"efs_filesystems":{},"s3_buckets":{"fsc-vault-backend-us-east-1":{"access_key_enabled":true,"access_key_id":null,"access_key_id_ssm_path":null,"account_id":"734995239048","account_json_key":"Transit","accounts":["Transit"],"acl":"private","additional_tag_map":{},"allow_encrypted_uploads_only":false,"allow_ssl_requests_only":false,"allowed_bucket_actions":["s3:PutObject"],"attributes":"private","block_public_acls":true,"block_public_policy":true,"bucket_arn":"arn:aws:s3:::fsc-vault-backend-us-east-1","bucket_domain_name":"fsc-vault-backend-us-east-1.s3.amazonaws.com","bucket_id":"fsc-vault-backend-us-east-1","bucket_key_enabled":false,"bucket_name":null,"bucket_region":"us-east-1","bucket_regional_domain_name":"fsc-vault-backend-us-east-1.s3.amazonaws.com","bucket_website_domain":"","bucket_website_endpoint":"","category":"s3_buckets","context":{"additional_tag_map":{},"attributes":["private"],"delimiter":null,"descriptor_formats":{},"enabled":true,"environment":"network","id_length_limit":null,"label_key_case":null,"label_order":["name","stage"],"label_value_case":null,"labels_as_tags":["default"],"name":"fsc-vault-backend","namespace":null,"regex_replace_chars":null,"stage":"us-east-1","tags":{"Environment":"network","Organization":"FlipsideCrypto","Owner":"DevOps","Stage":"us-east-1","Terraform":"terraform"},"tenant":null},"cors_configuration":[],"delimiter":null,"delivery_stream":false,"delivery_stream_arn":"","delivery_stream_name":"","descriptor_formats":{},"descriptors":{},"enabled":true,"environment":"network","execution_role_arn":"arn:aws:iam::734995239048:role/AWSControlTowerExecution","extra_grants":{},"force_destroy":false,"grant_organization_access":false,"grants":[],"id":"fsc-vault-backend-us-east-1","id_full":"fsc-vault-backend-us-east-1","id_length_limit":null,"ignore_public_acls":true,"kms_master_key_arn":"","label_order":["name","stage"],"logging":null,"managed":true,"max_days":0,"max_noncurrent_days":7,"max_noncurrent_versions":1,"name":"fsc-vault-backend-us-east-1","namespace":null,"network_map":{},"noncurrent_transition_after":0,"noncurrent_transition_to":"","normalized_context":{"additional_tag_map":{},"attributes":["private"],"delimiter":"-","descriptor_formats":{},"enabled":true,"environment":"network","id_length_limit":0,"label_key_case":"title","label_order":["name","stage"],"label_value_case":"lower","labels_as_tags":["attributes","environment","name","namespace","stage","tenant"],"name":"fsc-vault-backend","namespace":"","regex_replace_chars":"/[^-a-zA-Z0-9]/","stage":"us-east-1","tags":{"Attributes":"private","Environment":"network","Name":"fsc-vault-backend-us-east-1","Organization":"FlipsideCrypto","Owner":"DevOps","Stage":"us-east-1","Terraform":"terraform"},"tenant":""},"object_lock_configuration":null,"organization":"FlipsideCrypto","owner":"DevOps","private":true,"privileged_principal_actions":[],"privileged_principal_arns":[],"public":false,"regex_replace_chars":null,"replication_role_arn":"","restrict_public_buckets":true,"s3_object_ownership":"ObjectWriter","s3_replica_bucket_arn":"","s3_replication_enabled":false,"s3_replication_rules":[],"s3_replication_source_roles":[],"secret_access_key":"","secret_access_key_ssm_path":null,"short_name":"fsc-vault-backend","skip_grants":false,"source_policy_documents":[],"sse_algorithm":"aws:kms","ssm_base_path":"/s3_user/","ssm_parameters":["/infrastructure/Transit/s3_buckets/fsc-vault-backend-us-east-1/bucket_arn","/infrastructure/Transit/s3_buckets/fsc-vault-backend-us-east-1/bucket_id"],"ssm_path_prefix":"/infrastructure/Transit/s3_buckets","stage":"us-east-1","store_access_key_in_ssm":false,"tags":{},"tags_as_list_of_maps":[{"key":"Attributes","value":"private"},{"key":"Environment","value":"network"},{"key":"Name","value":"fsc-vault-backend-us-east-1"},{"key":"Organization","value":"FlipsideCrypto"},{"key":"Owner","value":"DevOps"},{"key":"Stage","value":"us-east-1"},{"key":"Terraform","value":"terraform"}],"tenant":null,"terraform":"terraform","traffic":"private","transfer_acceleration_enabled":false,"transition_after":0,"transition_to":"GLACIER","user_arn":"","user_enabled":false,"user_name":"","user_unique_id":"","versioning_enabled":true,"website_configuration":[],"website_redirect_all_requests_to":[]}}},"Vault":{"access_logs":{"vault-access-logs-flipside-crypto":{"bucket_arn":"arn:aws:s3:::vault-access-logs-flipside-crypto","bucket_domain_name":"vault-access-logs-flipside-crypto.s3.amazonaws.com","bucket_id":"vault-access-logs-flipside-crypto","bucket_prefix":"","enabled":true}},"efs_filesystems":{},"s3_buckets":{"fsc-vault-us-east-1":{"access_key_enabled":true,"access_key_id":null,"access_key_id_ssm_path":null,"account_id":"112841369362","account_json_key":"Vault","accounts":["Vault"],"acl":"private","additional_tag_map":{},"allow_encrypted_uploads_only":false,"allow_ssl_requests_only":false,"allowed_bucket_actions":["s3:PutObject"],"attributes":"private","block_public_acls":true,"block_public_policy":true,"bucket_arn":"arn:aws:s3:::fsc-vault-us-east-1","bucket_domain_name":"fsc-vault-us-east-1.s3.amazonaws.com","bucket_id":"fsc-vault-us-east-1","bucket_key_enabled":false,"bucket_name":null,"bucket_region":"us-east-1","bucket_regional_domain_name":"fsc-vault-us-east-1.s3.amazonaws.com","bucket_website_domain":"","bucket_website_endpoint":"","category":"s3_buckets","context":{"additional_tag_map":{},"attributes":["private"],"delimiter":null,"descriptor_formats":{},"enabled":true,"environment":"vault","id_length_limit":null,"label_key_case":null,"label_order":["name","stage"],"label_value_case":null,"labels_as_tags":["default"],"name":"fsc-vault","namespace":null,"regex_replace_chars":null,"stage":"us-east-1","tags":{"Environment":"vault","Organization":"FlipsideCrypto","Owner":"DevOps","Stage":"us-east-1","Terraform":"terraform"},"tenant":null},"cors_configuration":[],"delimiter":null,"delivery_stream":false,"delivery_stream_arn":"","delivery_stream_name":"","descriptor_formats":{},"descriptors":{},"enabled":true,"environment":"vault","execution_role_arn":"arn:aws:iam::112841369362:role/AWSControlTowerExecution","extra_grants":{},"force_destroy":false,"grant_organization_access":false,"grants":[],"id":"fsc-vault-us-east-1","id_full":"fsc-vault-us-east-1","id_length_limit":null,"ignore_public_acls":true,"kms_master_key_arn":"","label_order":["name","stage"],"logging":null,"managed":true,"max_days":0,"max_noncurrent_days":7,"max_noncurrent_versions":1,"name":"fsc-vault-us-east-1","namespace":null,"network_map":{},"noncurrent_transition_after":0,"noncurrent_transition_to":"","normalized_context":{"additional_tag_map":{},"attributes":["private"],"delimiter":"-","descriptor_formats":{},"enabled":true,"environment":"vault","id_length_limit":0,"label_key_case":"title","label_order":["name","stage"],"label_value_case":"lower","labels_as_tags":["attributes","environment","name","namespace","stage","tenant"],"name":"fsc-vault","namespace":"","regex_replace_chars":"/[^-a-zA-Z0-9]/","stage":"us-east-1","tags":{"Attributes":"private","Environment":"vault","Name":"fsc-vault-us-east-1","Organization":"FlipsideCrypto","Owner":"DevOps","Stage":"us-east-1","Terraform":"terraform"},"tenant":""},"object_lock_configuration":null,"organization":"FlipsideCrypto","owner":"DevOps","private":true,"privileged_principal_actions":[],"privileged_principal_arns":[],"public":false,"regex_replace_chars":null,"replication_role_arn":"","restrict_public_buckets":true,"s3_object_ownership":"ObjectWriter","s3_replica_bucket_arn":"","s3_replication_enabled":false,"s3_replication_rules":[],"s3_replication_source_roles":[],"secret_access_key":"","secret_access_key_ssm_path":null,"short_name":"fsc-vault","skip_grants":false,"source_policy_documents":[],"sse_algorithm":"aws:kms","ssm_base_path":"/s3_user/","ssm_parameters":["/infrastructure/Vault/s3_buckets/fsc-vault-us-east-1/bucket_arn","/infrastructure/Vault/s3_buckets/fsc-vault-us-east-1/bucket_id"],"ssm_path_prefix":"/infrastructure/Vault/s3_buckets","stage":"us-east-1","store_access_key_in_ssm":false,"tags":{},"tags_as_list_of_maps":[{"key":"Attributes","value":"private"},{"key":"Environment","value":"vault"},{"key":"Name","value":"fsc-vault-us-east-1"},{"key":"Organization","value":"FlipsideCrypto"},{"key":"Owner","value":"DevOps"},{"key":"Stage","value":"us-east-1"},{"key":"Terraform","value":"terraform"}],"tenant":null,"terraform":"terraform","traffic":"private","transfer_acceleration_enabled":false,"transition_after":0,"transition_to":"GLACIER","user_arn":"","user_enabled":false,"user_name":"","user_unique_id":"","versioning_enabled":true,"website_configuration":[],"website_redirect_all_requests_to":[]}}},"content_hub":{"access_logs":{"contenthub-access-logs-flipside-crypto":{"bucket_arn":"arn:aws:s3:::contenthub-access-logs-flipside-crypto","bucket_domain_name":"contenthub-access-logs-flipside-crypto.s3.amazonaws.com","bucket_id":"contenthub-access-logs-flipside-crypto","bucket_prefix":"","enabled":true}},"efs_filesystems":{},"s3_buckets":{}},"treasury_fireblocks_cosigners":{"access_logs":{"treasuryfireblockscosigners-access-logs-flipside-crypto":{"bucket_arn":"arn:aws:s3:::treasuryfireblockscosigners-access-logs-flipside-crypto","bucket_domain_name":"treasuryfireblockscosigners-access-logs-flipside-crypto.s3.amazonaws.com","bucket_id":"treasuryfireblockscosigners-access-logs-flipside-crypto","bucket_prefix":"","enabled":true}},"efs_filesystems":{"global-us-east-1-prodfireblockscosigners-private":{"access_point_arns":{"cosigner":"arn:aws:elasticfilesystem:us-east-1:084215729456:access-point/fsap-0e962b956a6a567e4","databases":"arn:aws:elasticfilesystem:us-east-1:084215729456:access-point/fsap-063d62d49e5bffce5"},"access_point_ids":{"cosigner":"fsap-0e962b956a6a567e4","databases":"fsap-063d62d49e5bffce5"},"access_points":{"cosigner":{"creation_info":{"gid":"2000","permissions":"0700","uid":"2000"},"posix_user":{"gid":"2000","uid":"2000"}},"databases":{"creation_info":{"gid":"2000","permissions":"0700","uid":"2000"},"posix_user":{"gid":"2000","uid":"2000"}}},"account_id":"084215729456","account_json_key":"treasury_fireblocks_cosigners","accounts":["treasury_fireblocks_cosigners"],"additional_security_group_rules":[],"additional_tag_map":{},"allowed_cidr_blocks":[],"allowed_security_group_ids":[],"arn":"arn:aws:elasticfilesystem:us-east-1:084215729456:file-system/fs-05cc25cf354fa044f","associated_security_group_ids":[],"attributes":"private","availability_zone_name":null,"category":"efs_filesystems","context":{"additional_tag_map":{},"attributes":["private"],"delimiter":null,"descriptor_formats":{},"enabled":true,"environment":"global","id_length_limit":null,"label_key_case":null,"label_order":[],"label_value_case":null,"labels_as_tags":["default"],"name":"prod_fireblocks_cosigners","namespace":null,"regex_replace_chars":null,"stage":"us-east-1","tags":{"Environment":"global","Organization":"FlipsideCrypto","Owner":"DevOps","Stage":"us-east-1","Terraform":"terraform"},"tenant":null},"create_security_group":true,"delimiter":null,"descriptor_formats":{},"descriptors":{},"dns_name":"","efs_backup_policy_enabled":true,"efs_cross_account_policy_enabled":false,"enabled":true,"encrypted":true,"environment":"global","execution_role_arn":"arn:aws:iam::084215729456:role/AWSControlTowerExecution","host":"","id":"fs-05cc25cf354fa044f","id_full":"global-us-east-1-prodfireblockscosigners-private","id_length_limit":null,"kms_key_id":"arn:aws:kms:us-east-1:084215729456:key/bb917354-6bcf-4118-a7b7-ac3a18034432","label_order":[],"mount_target_dns_names":["us-east-1a.fs-05cc25cf354fa044f.efs.us-east-1.amazonaws.com","us-east-1b.fs-05cc25cf354fa044f.efs.us-east-1.amazonaws.com","us-east-1c.fs-05cc25cf354fa044f.efs.us-east-1.amazonaws.com","us-east-1d.fs-05cc25cf354fa044f.efs.us-east-1.amazonaws.com","us-east-1e.fs-05cc25cf354fa044f.efs.us-east-1.amazonaws.com","us-east-1f.fs-05cc25cf354fa044f.efs.us-east-1.amazonaws.com"],"mount_target_ids":["fsmt-007cc1a802b1196b1","fsmt-0fec5cc19bc497dd0","fsmt-07c6f31c0ba81c924","fsmt-0fcf92a455165ddb5","fsmt-06445360d3c18581f","fsmt-0934e60faf479de31"],"mount_target_ip_address":null,"mount_target_ips":["10.128.130.76","10.128.132.230","10.128.139.157","10.128.140.216","10.128.147.52","10.128.151.251"],"name":"global-us-east-1-prodfireblockscosigners-private","namespace":null,"network_interface_ids":["eni-0d7295f2252933a3c","eni-01916adadbf9cc69a","eni-0696f065a328adcbf","eni-0adfa0d5b315217ca","eni-03a26dbc2cb07e006","eni-0505cad7a4d53e500"],"network_map":{},"normalized_context":{"additional_tag_map":{},"attributes":["private"],"delimiter":"-","descriptor_formats":{},"enabled":true,"environment":"global","id_length_limit":0,"label_key_case":"title","label_order":["namespace","environment","stage","name","attributes"],"label_value_case":"lower","labels_as_tags":["attributes","environment","name","namespace","stage","tenant"],"name":"prodfireblockscosigners","namespace":"","regex_replace_chars":"/[^-a-zA-Z0-9]/","stage":"us-east-1","tags":{"Attributes":"private","Environment":"global","Name":"global-us-east-1-prodfireblockscosigners-private","Organization":"FlipsideCrypto","Owner":"DevOps","Stage":"us-east-1","Terraform":"terraform"},"tenant":""},"organization":"FlipsideCrypto","owner":"DevOps","performance_mode":"generalPurpose","private":true,"provisioned_throughput_in_mibps":0,"public":false,"regex_replace_chars":null,"region":null,"security_group_arn":"arn:aws:ec2:us-east-1:084215729456:security-group/sg-0a059f1a3db964b08","security_group_create_before_destroy":true,"security_group_create_timeout":"10m","security_group_delete_timeout":"15m","security_group_description":"EFS Security Group","security_group_id":"sg-0a059f1a3db964b08","security_group_name":[],"short_name":"prod_fireblocks_cosigners","ssm_parameters":[],"ssm_path_prefix":"/infrastructure/treasury_fireblocks_cosigners/efs_filesystems","stage":"us-east-1","subnets":[],"tags":{},"tags_as_list_of_maps":[{"key":"Attributes","value":"private"},{"key":"Environment","value":"global"},{"key":"Name","value":"global-us-east-1-prodfireblockscosigners-private"},{"key":"Organization","value":"FlipsideCrypto"},{"key":"Owner","value":"DevOps"},{"key":"Stage","value":"us-east-1"},{"key":"Terraform","value":"terraform"}],"tenant":null,"terraform":"terraform","throughput_mode":"bursting","traffic":"private","transition_to_ia":["AFTER_90_DAYS"],"transition_to_primary_storage_class":[],"vpc_id":null,"zone_id":[]},"global-us-east-1-stgfireblockscosigners-private":{"access_point_arns":{"cosigner":"arn:aws:elasticfilesystem:us-east-1:084215729456:access-point/fsap-0a834c58ae696d996","databases":"arn:aws:elasticfilesystem:us-east-1:084215729456:access-point/fsap-0922babc6f038ac23"},"access_point_ids":{"cosigner":"fsap-0a834c58ae696d996","databases":"fsap-0922babc6f038ac23"},"access_points":{"cosigner":{"creation_info":{"gid":"2000","permissions":"0700","uid":"2000"},"posix_user":{"gid":"2000","uid":"2000"}},"databases":{"creation_info":{"gid":"2000","permissions":"0700","uid":"2000"},"posix_user":{"gid":"2000","uid":"2000"}}},"account_id":"084215729456","account_json_key":"treasury_fireblocks_cosigners","accounts":["treasury_fireblocks_cosigners"],"additional_security_group_rules":[],"additional_tag_map":{},"allowed_cidr_blocks":[],"allowed_security_group_ids":[],"arn":"arn:aws:elasticfilesystem:us-east-1:084215729456:file-system/fs-0de86a62f196d1356","associated_security_group_ids":[],"attributes":"private","availability_zone_name":null,"category":"efs_filesystems","context":{"additional_tag_map":{},"attributes":["private"],"delimiter":null,"descriptor_formats":{},"enabled":true,"environment":"global","id_length_limit":null,"label_key_case":null,"label_order":[],"label_value_case":null,"labels_as_tags":["default"],"name":"stg_fireblocks_cosigners","namespace":null,"regex_replace_chars":null,"stage":"us-east-1","tags":{"Environment":"global","Organization":"FlipsideCrypto","Owner":"DevOps","Stage":"us-east-1","Terraform":"terraform"},"tenant":null},"create_security_group":true,"delimiter":null,"descriptor_formats":{},"descriptors":{},"dns_name":"","efs_backup_policy_enabled":true,"efs_cross_account_policy_enabled":false,"enabled":true,"encrypted":true,"environment":"global","execution_role_arn":"arn:aws:iam::084215729456:role/AWSControlTowerExecution","host":"","id":"fs-0de86a62f196d1356","id_full":"global-us-east-1-stgfireblockscosigners-private","id_length_limit":null,"kms_key_id":"arn:aws:kms:us-east-1:084215729456:key/df984c52-90f2-43f2-9cdf-fc16c5a030d8","label_order":[],"mount_target_dns_names":["us-east-1a.fs-0de86a62f196d1356.efs.us-east-1.amazonaws.com","us-east-1b.fs-0de86a62f196d1356.efs.us-east-1.amazonaws.com","us-east-1c.fs-0de86a62f196d1356.efs.us-east-1.amazonaws.com","us-east-1d.fs-0de86a62f196d1356.efs.us-east-1.amazonaws.com","us-east-1e.fs-0de86a62f196d1356.efs.us-east-1.amazonaws.com","us-east-1f.fs-0de86a62f196d1356.efs.us-east-1.amazonaws.com"],"mount_target_ids":["fsmt-00c014c49347148f5","fsmt-00c38c597e602625b","fsmt-048685fd2b5218b62","fsmt-09e48b6702cb3a729","fsmt-068c1d354d5270b9c","fsmt-0372a2e001e876562"],"mount_target_ip_address":null,"mount_target_ips":["10.128.130.161","10.128.132.158","10.128.136.138","10.128.140.39","10.128.145.141","10.128.149.225"],"name":"global-us-east-1-stgfireblockscosigners-private","namespace":null,"network_interface_ids":["eni-00a9b7cc0648901c4","eni-0a4ff21d996b3873d","eni-03c9610ccc3ab1eb7","eni-0c2fbdb3fb28bafb9","eni-014bce90df95ec39f","eni-01e185a0ccbae5980"],"network_map":{},"normalized_context":{"additional_tag_map":{},"attributes":["private"],"delimiter":"-","descriptor_formats":{},"enabled":true,"environment":"global","id_length_limit":0,"label_key_case":"title","label_order":["namespace","environment","stage","name","attributes"],"label_value_case":"lower","labels_as_tags":["attributes","environment","name","namespace","stage","tenant"],"name":"stgfireblockscosigners","namespace":"","regex_replace_chars":"/[^-a-zA-Z0-9]/","stage":"us-east-1","tags":{"Attributes":"private","Environment":"global","Name":"global-us-east-1-stgfireblockscosigners-private","Organization":"FlipsideCrypto","Owner":"DevOps","Stage":"us-east-1","Terraform":"terraform"},"tenant":""},"organization":"FlipsideCrypto","owner":"DevOps","performance_mode":"generalPurpose","private":true,"provisioned_throughput_in_mibps":0,"public":false,"regex_replace_chars":null,"region":null,"security_group_arn":"arn:aws:ec2:us-east-1:084215729456:security-group/sg-0fa4290d228eafd6d","security_group_create_before_destroy":true,"security_group_create_timeout":"10m","security_group_delete_timeout":"15m","security_group_description":"EFS Security Group","security_group_id":"sg-0fa4290d228eafd6d","security_group_name":[],"short_name":"stg_fireblocks_cosigners","ssm_parameters":[],"ssm_path_prefix":"/infrastructure/treasury_fireblocks_cosigners/efs_filesystems","stage":"us-east-1","subnets":[],"tags":{},"tags_as_list_of_maps":[{"key":"Attributes","value":"private"},{"key":"Environment","value":"global"},{"key":"Name","value":"global-us-east-1-stgfireblockscosigners-private"},{"key":"Organization","value":"FlipsideCrypto"},{"key":"Owner","value":"DevOps"},{"key":"Stage","value":"us-east-1"},{"key":"Terraform","value":"terraform"}],"tenant":null,"terraform":"terraform","throughput_mode":"bursting","traffic":"private","transition_to_ia":["AFTER_90_DAYS"],"transition_to_primary_storage_class":[],"vpc_id":null,"zone_id":[]}},"s3_buckets":{}}}