{"access_points":{},"account_id":null,"accounts":["Staging","Production"],"additional_security_group_rules":[],"additional_tag_map":{},"allowed_cidr_blocks":[],"allowed_security_group_ids":[],"associated_security_group_ids":[],"attributes":[],"availability_zone_name":null,"create_security_group":true,"delimiter":null,"descriptor_formats":{},"dns_name":"","efs_backup_policy_enabled":true,"enabled":true,"encrypted":true,"environment":null,"execution_role_arn":"","id_length_limit":null,"kms_key_id":null,"mount_target_ip_address":null,"name":null,"namespace":null,"performance_mode":"generalPurpose","private":false,"provisioned_throughput_in_mibps":0,"public":false,"regex_replace_chars":null,"region":null,"security_group_create_before_destroy":true,"security_group_create_timeout":"10m","security_group_delete_timeout":"15m","security_group_description":"EFS Security Group","security_group_name":[],"stage":null,"subnets":[],"tags":{},"tenant":null,"throughput_mode":"bursting","transition_to_ia":[],"transition_to_primary_storage_class":[],"vpc_id":null,"zone_id":[]}